nbdev_project/__init__.py
nbdev_project/_modidx.py
nbdev_project/card.py
nbdev_project/deck.py
nbdev_project-0.0.1.dist-info/LICENSE
nbdev_project-0.0.1.dist-info/METADATA
nbdev_project-0.0.1.dist-info/WHEEL
nbdev_project-0.0.1.dist-info/entry_points.txt
nbdev_project-0.0.1.dist-info/top_level.txt
nbdev_project-0.0.1.dist-info/RECORD
